wallet_tool/__init__.py
wallet_tool/mylib.py
wallet_tool/wallet_tool.py
wallet_tool-0.6.dist-info/LICENSE
wallet_tool-0.6.dist-info/METADATA
wallet_tool-0.6.dist-info/WHEEL
wallet_tool-0.6.dist-info/top_level.txt
wallet_tool-0.6.dist-info/RECORD
