Metadata-Version: 2.1
Name: wallet_tool
Version: 0.6
Summary: This is a web3 wallet operation tool
Home-page: https://github.com/embzheng/wallet_tool
Author: embzheng
Author-email: embzheng@qq.com
Project-URL: Source, https://github.com/embzheng/wallet_tool
Classifier: Programming Language :: Python :: 3
Classifier: License :: OSI Approved :: MIT License
Classifier: Operating System :: OS Independent
License-File: LICENSE
Requires-Dist: playwright >=1.42.0
Requires-Dist: sys
Requires-Dist: random
Requires-Dist: my-logtool
Requires-Dist: bitbrowser-tool
